tencat/__init__.py
tencat/tencat.py
tencat-0.3.dist-info/LICENSE
tencat-0.3.dist-info/METADATA
tencat-0.3.dist-info/WHEEL
tencat-0.3.dist-info/top_level.txt
tencat-0.3.dist-info/RECORD
