Metadata-Version: 2.1
Name: tencat
Version: 0.3
Summary: tencat is a python package that offers functionality to slice sparse tensors
Home-page: https://github.com/NixtonM/TenCat
Author: Nicholas Meyer, Agniezka Rozniak, Pia Ruttner
Author-email: meyernic@student.ethz.ch, rozniaka@student.ethz.ch, ruttnerp@student.ethz.ch
License: MIT
Platform: UNKNOWN
Classifier: Development Status :: 3 - Alpha
Classifier: License :: OSI Approved :: MIT License
Classifier: Programming Language :: Python
Classifier: Programming Language :: Python :: 3.6
Classifier: Programming Language :: Python :: 3.7
Classifier: Topic :: Software Development :: Libraries
Classifier: Topic :: Software Development :: Libraries :: Python Modules
Classifier: Intended Audience :: Developers
Requires-Python: >=3.6
Requires-Dist: numpy
